mowao.cpython-314-x86_64-linux-gnu.so
mowao-0.0.2.dist-info/METADATA
mowao-0.0.2.dist-info/WHEEL
mowao-0.0.2.dist-info/top_level.txt
mowao-0.0.2.dist-info/RECORD
mowao-0.0.2.dist-info/licenses/LICENSE
