Metadata-Version: 2.4
Name: mowao
Version: 0.0.2
Summary: Multi-objective WAO algorithm
Author-email: Arman Daliri <daliriwork2@gmail.com>
Maintainer-email: Mohammad Mahdi Mir <m.m.mir83hc@gmail.com>
License-Expression: MIT
Project-URL: source, https://github.com/arman-daliri/MOWAO
Classifier: Topic :: Scientific/Engineering
Classifier: Intended Audience :: Science/Research
Classifier: Programming Language :: C
Classifier: Operating System :: POSIX :: Linux
Classifier: Operating System :: Microsoft :: Windows
Requires-Python: >=3.12
License-File: LICENSE
Dynamic: license-file
